MANIFEST.in
README.md
setup.cfg
setup.py
pytorch_block_sparse/__init__.py
pytorch_block_sparse/block_sparse.py
pytorch_block_sparse/block_sparse_linear.py
pytorch_block_sparse/util.py
pytorch_block_sparse.egg-info/PKG-INFO
pytorch_block_sparse.egg-info/SOURCES.txt
pytorch_block_sparse.egg-info/dependency_links.txt
pytorch_block_sparse.egg-info/not-zip-safe
pytorch_block_sparse.egg-info/top_level.txt
pytorch_block_sparse/cutlass/gemm/block_loader.h
pytorch_block_sparse/cutlass/gemm/block_loader_congruous_dp1.h
pytorch_block_sparse/cutlass/gemm/block_loader_congruous_dp1_prune_sparse.h
pytorch_block_sparse/cutlass/gemm/block_loader_crosswise.h
pytorch_block_sparse/cutlass/gemm/block_loader_crosswise_prune_dense.h
pytorch_block_sparse/cutlass/gemm/block_task.h
pytorch_block_sparse/cutlass/gemm/block_task_back.h
pytorch_block_sparse/cutlass/gemm/block_task_back_full.h
pytorch_block_sparse/cutlass/gemm/dispatch.h
pytorch_block_sparse/cutlass/gemm/dispatch_back.h
pytorch_block_sparse/cutlass/gemm/dispatch_back_full.h
pytorch_block_sparse/cutlass/gemm/dispatch_policies.h
pytorch_block_sparse/cutlass/gemm/dp_accummulate.h
pytorch_block_sparse/cutlass/gemm/epilogue_function.h
pytorch_block_sparse/cutlass/gemm/grid_raster.h
pytorch_block_sparse/cutlass/gemm/grid_raster_sparse.h
pytorch_block_sparse/cutlass/gemm/k_split_control.h
pytorch_block_sparse/cutlass/gemm/thread_accumulator.h
pytorch_block_sparse/cutlass/gemm/back/block_loader.h
pytorch_block_sparse/cutlass/gemm/back/block_loader_congruous_dp1.h
pytorch_block_sparse/cutlass/gemm/back/block_loader_congruous_dp1_prune.h
pytorch_block_sparse/cutlass/gemm/back/block_loader_crosswise.h
pytorch_block_sparse/cutlass/gemm/back/block_loader_crosswise_prune.h
pytorch_block_sparse/cutlass/gemm/back/block_task.h
pytorch_block_sparse/cutlass/gemm/back/block_task_back.h
pytorch_block_sparse/cutlass/gemm/back/block_task_back_full.h
pytorch_block_sparse/cutlass/gemm/back/dispatch.h
pytorch_block_sparse/cutlass/gemm/back/dispatch_back.h
pytorch_block_sparse/cutlass/gemm/back/dispatch_back_full.h
pytorch_block_sparse/cutlass/gemm/back/dispatch_policies.h
pytorch_block_sparse/cutlass/gemm/back/dp_accummulate.h
